Workbook

Sheet Task List
A1: Major Stat | B1: Minor Stat | C1: Category | D1: Subcategory | E1: Difficulty | F1: Base success | G1: Major Reward | H1: Minor Reward | I1: Penalty | J1: Prerequisite | K1: Description | L1: Success Description | M1: Failure Description
A2: =VLOOKUP(C2,'Lookup tables'!$A$2:$B$5,2,0) -> Relevance | B2: Fame | C2: Show | D2: Club | E2: Easy | F2: =VLOOKUP(E2,'Lookup tables'!$O$2:$P$4,2,0) -> 0.75 | G2: =_xlfn.CONCAT(VLOOKUP(E2,'Lookup tables'!$O$2:$Q$4,3,0)*VLOOKUP($G$1,'Lookup tables'!$K$1:$L$2,2,0)," ",A2) -> 2 Relevance | H2: =_xlfn.CONCAT(VLOOKUP(E2,'Lookup tables'!$O$2:$Q$4,3,0)*VLOOKUP($H$1,'Lookup tables'!$K$1:$L$2,2,0)," ",B2) -> 1 Fame | I2: =_xlfn.CONCAT('Lookup tables'!$L$6*VLOOKUP(E2,'Lookup tables'!$O$2:$Q$4,3,0)," ",A2) -> -1 Relevance | J2: =_xlfn.CONCAT(VLOOKUP(E2,'Lookup tables'!$O$2:$R$4,4,0)," ",A2) -> 10 Relevance | K2: The house band’s lead singer at the Flashlight have all caught a dose of botulism. Here’s a list of songs; go and fill in. | L2: Nice job! You looked pretty good up there. If they need someone to fill in you’ll be the one to call! | M2: Oh dear me. Well, we all die on our arse sometimes, but at least it’s on someone else’s billing rather than your own. Onward and upward. Or not, as the case may be…
A3: =VLOOKUP(C3,'Lookup tables'!$A$2:$B$5,2,0) -> Relevance | B3: Money | C3: Show | D3: =VLOOKUP(_xlfn.CONCAT(A3,B3),'Lookup tables'!$G$2:$H$13,2,0) -> Gig | E3: Easy | F3: =VLOOKUP(E3,'Lookup tables'!$O$2:$P$4,2,0) -> 0.75 | G3: =_xlfn.CONCAT(VLOOKUP(E3,'Lookup tables'!$O$2:$Q$4,3,0)*VLOOKUP($G$1,'Lookup tables'!$K$1:$L$2,2,0)," ",A3) -> 2 Relevance | H3: =_xlfn.CONCAT(VLOOKUP(E3,'Lookup tables'!$O$2:$Q$4,3,0)*VLOOKUP($H$1,'Lookup tables'!$K$1:$L$2,2,0)," ",B3) -> 1 Money | I3: =_xlfn.CONCAT('Lookup tables'!$L$6*VLOOKUP(E3,'Lookup tables'!$O$2:$Q$4,3,0)," ",A3) -> -1 Relevance | J3: =_xlfn.CONCAT(VLOOKUP(E3,'Lookup tables'!$O$2:$R$4,4,0)," ",A3) -> 10 Relevance | K3: Barry Prunk’s singing at the Velour this Friday. He needs a support act, somehow your name came up. | L3: Barry Who? Someone stole the show a bit there, didn’t they? Still, at least he took it in his stride. Just don’t be too hurt if he goes for someone cheaper next time. | M3: Barry Prunk got where he is today by being grateful. And right now… he’s grateful that you made him look good. Even better, in fact. Compared to you he was the Second Coming.
A4: =VLOOKUP(C4,'Lookup tables'!$A$2:$B$5,2,0) -> Relevance | B4: Fun | C4: Show | D4: =VLOOKUP(_xlfn.CONCAT(A4,B4),'Lookup tables'!$G$2:$H$13,2,0) -> Festival | E4: Easy | F4: =VLOOKUP(E4,'Lookup tables'!$O$2:$P$4,2,0) -> 0.75 | G4: =_xlfn.CONCAT(VLOOKUP(E4,'Lookup tables'!$O$2:$Q$4,3,0)*VLOOKUP($G$1,'Lookup tables'!$K$1:$L$2,2,0)," ",A4) -> 2 Relevance | H4: =_xlfn.CONCAT(VLOOKUP(E4,'Lookup tables'!$O$2:$Q$4,3,0)*VLOOKUP($H$1,'Lookup tables'!$K$1:$L$2,2,0)," ",B4) -> 1 Fun | I4: =_xlfn.CONCAT('Lookup tables'!$L$6*VLOOKUP(E4,'Lookup tables'!$O$2:$Q$4,3,0)," ",A4) -> -1 Relevance | J4: =_xlfn.CONCAT(VLOOKUP(E4,'Lookup tables'!$O$2:$R$4,4,0)," ",A4) -> 10 Relevance | K4: You know the Offload Festival? The one that’s never on at a consistent time? You’ve got a spot on the Wobbly Stage. After the main act. It’s better than nothing. Just. | L4: Not a headline show, but you know what? You weren’t just a last-minute fill-in. Well, you WERE, but nobody’s gonna say that out loud now. | M4: You see how the audience cheered when they started taking the stage down? … yeah. They’re calling you the Rigger’s Friend now.
A5: =VLOOKUP(C5,'Lookup tables'!$A$2:$B$5,2,0) -> Fame | B5: Relevance | C5: Media | D5: =VLOOKUP(_xlfn.CONCAT(A5,B5),'Lookup tables'!$G$2:$H$13,2,0) -> TV | E5: Easy | F5: =VLOOKUP(E5,'Lookup tables'!$O$2:$P$4,2,0) -> 0.75 | G5: =_xlfn.CONCAT(VLOOKUP(E5,'Lookup tables'!$O$2:$Q$4,3,0)*VLOOKUP($G$1,'Lookup tables'!$K$1:$L$2,2,0)," ",A5) -> 2 Fame | H5: =_xlfn.CONCAT(VLOOKUP(E5,'Lookup tables'!$O$2:$Q$4,3,0)*VLOOKUP($H$1,'Lookup tables'!$K$1:$L$2,2,0)," ",B5) -> 1 Relevance | I5: =_xlfn.CONCAT('Lookup tables'!$L$6*VLOOKUP(E5,'Lookup tables'!$O$2:$Q$4,3,0)," ",A5) -> -1 Fame | J5: =_xlfn.CONCAT(VLOOKUP(E5,'Lookup tables'!$O$2:$R$4,4,0)," ",A5) -> 10 Fame | K5: We’re going to shoot a music video. Well, no, we’re going to shoot bits of a music video; a bunch of 15-second things and put them on the short-form sites for kids to find. If we make our money back we’ll shoot the whole thing. | L5: Lots and lots of views, lots of ads viewed, and… well, looks like we got a video out of it. I’ve got a headache, I barely understand it, but I understand money and attention and on that score… this was a nice little earner. | M5: Plop. Plop. Plop. Plop. One by one the clips go into the depths, unseen, unremarked-on, unthumbed… unpaid. We’d better try something else, eh?
A6: =VLOOKUP(C6,'Lookup tables'!$A$2:$B$5,2,0) -> Fame | B6: Money | C6: Media | D6: =VLOOKUP(_xlfn.CONCAT(A6,B6),'Lookup tables'!$G$2:$H$13,2,0) -> Podcast | E6: Easy | F6: =VLOOKUP(E6,'Lookup tables'!$O$2:$P$4,2,0) -> 0.75 | G6: =_xlfn.CONCAT(VLOOKUP(E6,'Lookup tables'!$O$2:$Q$4,3,0)*VLOOKUP($G$1,'Lookup tables'!$K$1:$L$2,2,0)," ",A6) -> 2 Fame | H6: =_xlfn.CONCAT(VLOOKUP(E6,'Lookup tables'!$O$2:$Q$4,3,0)*VLOOKUP($H$1,'Lookup tables'!$K$1:$L$2,2,0)," ",B6) -> 1 Money | I6: =_xlfn.CONCAT('Lookup tables'!$L$6*VLOOKUP(E6,'Lookup tables'!$O$2:$Q$4,3,0)," ",A6) -> -1 Fame | J6: =_xlfn.CONCAT(VLOOKUP(E6,'Lookup tables'!$O$2:$R$4,4,0)," ",A6) -> 10 Fame | K6: You know that genre of music you say you do? Well, turns out there’s a podcast for it now. Joey’s Fart Sandwich. I’ve never heard of it either but they’ll have to pretend to listen to you for half an hour so I said okay. | L6: That was the biggest load of old bollocks I’ve ever heard anyone talk in years. You made no sense, nobody followed it, but they’ll all pretend they did for fear of looking stupid. You’re a natural. Let’s do another! | M6: You know that bit where Joey said ‘let’s be real’ and ‘let’s talk like normal people’? He was an idiot for saying that, and you were an idiot for doing it! The whole thing fell flat within five minutes.
A7: =VLOOKUP(C7,'Lookup tables'!$A$2:$B$5,2,0) -> Fame | B7: Fun | C7: Media | D7: =VLOOKUP(_xlfn.CONCAT(A7,B7),'Lookup tables'!$G$2:$H$13,2,0) -> Stream | E7: Easy | F7: =VLOOKUP(E7,'Lookup tables'!$O$2:$P$4,2,0) -> 0.75 | G7: =_xlfn.CONCAT(VLOOKUP(E7,'Lookup tables'!$O$2:$Q$4,3,0)*VLOOKUP($G$1,'Lookup tables'!$K$1:$L$2,2,0)," ",A7) -> 2 Fame | H7: =_xlfn.CONCAT(VLOOKUP(E7,'Lookup tables'!$O$2:$Q$4,3,0)*VLOOKUP($H$1,'Lookup tables'!$K$1:$L$2,2,0)," ",B7) -> 1 Fun | I7: =_xlfn.CONCAT('Lookup tables'!$L$6*VLOOKUP(E7,'Lookup tables'!$O$2:$Q$4,3,0)," ",A7) -> -1 Fame | J7: =_xlfn.CONCAT(VLOOKUP(E7,'Lookup tables'!$O$2:$R$4,4,0)," ",A7) -> 10 Fame | K7: What’s that video game you like to play? The one I can’t get you to shut up about? Yeah, this is a different game, but it’s an hour of publicity. If nothing else you can try to make it all about you. | L7: That’s the thing about video games: you don’t have to be good at them. You have to be good at doing other stuff while playing them. If you can talk bollocks while everyone else kicks your arse and entertain that way, you’ve got it made. | M7: Yeah, you realise they weren’t actually bringing you in to be good at video games, right? They were bringing you in to entertain. Try and manage something beyond a few adolescent grunts next time and you’ll have a better time of it.
A8: =VLOOKUP(C8,'Lookup tables'!$A$2:$B$5,2,0) -> Money | B8: Relevance | C8: Recording | D8: =VLOOKUP(_xlfn.CONCAT(A8,B8),'Lookup tables'!$G$2:$H$13,2,0) -> Collaboration | E8: Easy | F8: =VLOOKUP(E8,'Lookup tables'!$O$2:$P$4,2,0) -> 0.75 | G8: =_xlfn.CONCAT(VLOOKUP(E8,'Lookup tables'!$O$2:$Q$4,3,0)*VLOOKUP($G$1,'Lookup tables'!$K$1:$L$2,2,0)," ",A8) -> 2 Money | H8: =_xlfn.CONCAT(VLOOKUP(E8,'Lookup tables'!$O$2:$Q$4,3,0)*VLOOKUP($H$1,'Lookup tables'!$K$1:$L$2,2,0)," ",B8) -> 1 Relevance | I8: =_xlfn.CONCAT('Lookup tables'!$L$6*VLOOKUP(E8,'Lookup tables'!$O$2:$Q$4,3,0)," ",A8) -> -1 Money | J8: =_xlfn.CONCAT(VLOOKUP(E8,'Lookup tables'!$O$2:$R$4,4,0)," ",A8) -> 10 Money | K8: Rebecca Lisk liked your voice on that thing you did whose name no-one remembers. You’ve got a guest spot on her album. | L8: Rebecca Lisk has no idea what she wants. That sounded awful, and not even the good kind of awful. Might be a bonus track years later, but I’m not betting on it! | M8: Looks like she liked that thing you did here too. On the one hand, more collabs; on the other you’re stuck with her if she does something really stupid. Feeling any regrets yet?
A9: =VLOOKUP(C9,'Lookup tables'!$A$2:$B$5,2,0) -> Money | B9: Fame | C9: Recording | D9: =VLOOKUP(_xlfn.CONCAT(A9,B9),'Lookup tables'!$G$2:$H$13,2,0) -> Single | E9: Easy | F9: =VLOOKUP(E9,'Lookup tables'!$O$2:$P$4,2,0) -> 0.75 | G9: =_xlfn.CONCAT(VLOOKUP(E9,'Lookup tables'!$O$2:$Q$4,3,0)*VLOOKUP($G$1,'Lookup tables'!$K$1:$L$2,2,0)," ",A9) -> 2 Money | H9: =_xlfn.CONCAT(VLOOKUP(E9,'Lookup tables'!$O$2:$Q$4,3,0)*VLOOKUP($H$1,'Lookup tables'!$K$1:$L$2,2,0)," ",B9) -> 1 Fame | I9: =_xlfn.CONCAT('Lookup tables'!$L$6*VLOOKUP(E9,'Lookup tables'!$O$2:$Q$4,3,0)," ",A9) -> -1 Money | J9: =_xlfn.CONCAT(VLOOKUP(E9,'Lookup tables'!$O$2:$R$4,4,0)," ",A9) -> 10 Money | K9: I think it’s time to record a demo and see if any of the companies are interested. | L9: Bloody Hell. You almost sounded like you could do this for a living! Just… just don’t play it at any parties you go to, alright? What’s the kids’ word for that these days? Cringe? Yeah. | M9: And it turns out not even the producer or the engineer were interested. What a waste of time!
A10: =VLOOKUP(C10,'Lookup tables'!$A$2:$B$5,2,0) -> Money | B10: Fun | C10: Recording | D10: =VLOOKUP(_xlfn.CONCAT(A10,B10),'Lookup tables'!$G$2:$H$13,2,0) -> Novelty | E10: Easy | F10: =VLOOKUP(E10,'Lookup tables'!$O$2:$P$4,2,0) -> 0.75 | G10: =_xlfn.CONCAT(VLOOKUP(E10,'Lookup tables'!$O$2:$Q$4,3,0)*VLOOKUP($G$1,'Lookup tables'!$K$1:$L$2,2,0)," ",A10) -> 2 Money | H10: =_xlfn.CONCAT(VLOOKUP(E10,'Lookup tables'!$O$2:$Q$4,3,0)*VLOOKUP($H$1,'Lookup tables'!$K$1:$L$2,2,0)," ",B10) -> 1 Fun | I10: =_xlfn.CONCAT('Lookup tables'!$L$6*VLOOKUP(E10,'Lookup tables'!$O$2:$Q$4,3,0)," ",A10) -> -1 Money | J10: =_xlfn.CONCAT(VLOOKUP(E10,'Lookup tables'!$O$2:$R$4,4,0)," ",A10) -> 10 Money | K10: Looks like every local act is clubbing together for a joke. Let’s get you behind the mic with them! | L10: It sounded awful, but it was a laugh and you were there. Your name’s on the credits and this time next year -- it’ll be an obscure question on a trivia quiz. | M10: You might at least have learned the words. What was it you did? “Freestyling?” That’s usually reserved for rappers.
A11: =VLOOKUP(C11,'Lookup tables'!$A$2:$B$5,2,0) -> Fun | B11: Relevance | C11: Publicity | D11: =VLOOKUP(_xlfn.CONCAT(A11,B11),'Lookup tables'!$G$2:$H$13,2,0) -> Viral | E11: Easy | F11: =VLOOKUP(E11,'Lookup tables'!$O$2:$P$4,2,0) -> 0.75 | G11: =_xlfn.CONCAT(VLOOKUP(E11,'Lookup tables'!$O$2:$Q$4,3,0)*VLOOKUP($G$1,'Lookup tables'!$K$1:$L$2,2,0)," ",A11) -> 2 Fun | H11: =_xlfn.CONCAT(VLOOKUP(E11,'Lookup tables'!$O$2:$Q$4,3,0)*VLOOKUP($H$1,'Lookup tables'!$K$1:$L$2,2,0)," ",B11) -> 1 Relevance | I11: =_xlfn.CONCAT('Lookup tables'!$L$6*VLOOKUP(E11,'Lookup tables'!$O$2:$Q$4,3,0)," ",A11) -> -1 Fun | J11: =_xlfn.CONCAT(VLOOKUP(E11,'Lookup tables'!$O$2:$R$4,4,0)," ",A11) -> 10 Fun | K11: It’s Karaoke Night at the Alhambra. You decide to sing a song that’s been making the rounds on YouTube. | L11: Nice going. Getting everyone else to join in is a great way to cover up the fact you forgot the words. | M11: … Baby Shark. Really. Yeah, let’s avoid the Alhambra for a bit. Maybe until it closes down.
A12: =VLOOKUP(C12,'Lookup tables'!$A$2:$B$5,2,0) -> Fun | B12: Fame | C12: Publicity | D12: =VLOOKUP(_xlfn.CONCAT(A12,B12),'Lookup tables'!$G$2:$H$13,2,0) -> Prank | E12: Easy | F12: =VLOOKUP(E12,'Lookup tables'!$O$2:$P$4,2,0) -> 0.75 | G12: =_xlfn.CONCAT(VLOOKUP(E12,'Lookup tables'!$O$2:$Q$4,3,0)*VLOOKUP($G$1,'Lookup tables'!$K$1:$L$2,2,0)," ",A12) -> 2 Fun | H12: =_xlfn.CONCAT(VLOOKUP(E12,'Lookup tables'!$O$2:$Q$4,3,0)*VLOOKUP($H$1,'Lookup tables'!$K$1:$L$2,2,0)," ",B12) -> 1 Fame | I12: =_xlfn.CONCAT('Lookup tables'!$L$6*VLOOKUP(E12,'Lookup tables'!$O$2:$Q$4,3,0)," ",A12) -> -1 Fun | J12: =_xlfn.CONCAT(VLOOKUP(E12,'Lookup tables'!$O$2:$R$4,4,0)," ",A12) -> 10 Fun | K12: Jimmy Oxter’s turning into a regular at your local club. See if you can catch him out with this whoopee cushion. | L12: Oh, his face! The laughter! Of course now his bodyguards say they’ll break your legs if you try it again, but they had a giggle too and we all saw them. | M12: … you were meant to get him to sit on it, not hit him with the bloody thing! What’s wrong with you?!
A13: =VLOOKUP(C13,'Lookup tables'!$A$2:$B$5,2,0) -> Fun | B13: Money | C13: Publicity | D13: Influencer | E13: Easy | F13: =VLOOKUP(E13,'Lookup tables'!$O$2:$P$4,2,0) -> 0.75 | G13: =_xlfn.CONCAT(VLOOKUP(E13,'Lookup tables'!$O$2:$Q$4,3,0)*VLOOKUP($G$1,'Lookup tables'!$K$1:$L$2,2,0)," ",A13) -> 2 Fun | H13: =_xlfn.CONCAT(VLOOKUP(E13,'Lookup tables'!$O$2:$Q$4,3,0)*VLOOKUP($H$1,'Lookup tables'!$K$1:$L$2,2,0)," ",B13) -> 1 Money | I13: =_xlfn.CONCAT('Lookup tables'!$L$6*VLOOKUP(E13,'Lookup tables'!$O$2:$Q$4,3,0)," ",A13) -> -1 Fun | J13: =_xlfn.CONCAT(VLOOKUP(E13,'Lookup tables'!$O$2:$R$4,4,0)," ",A13) -> 10 Fun | K13: Emmett Frogg, the guy who invented Fidget Flippers, is offering silly money for a couple of people to do a glorified ad. So we’re going to meet an influencer and play with some plastic frogs. | L13: There is something a bit compulsive about trying to make a plastic frog do a somersault, isn’t there? Nice job, he was able to empty his lockup within two days. | M13: Oh, bloody Hell. They’re small plastic frogs. Why did you put them in your mouth?! Now they’re being recalled as a choking hazard….
A14: =VLOOKUP(C14,'Lookup tables'!$A$2:$B$5,2,0) -> Relevance | B14: Fame | C14: Show | D14: Club | E14: Medium | F14: =VLOOKUP(E14,'Lookup tables'!$O$2:$P$4,2,0) -> 0.6 | G14: =_xlfn.CONCAT(VLOOKUP(E14,'Lookup tables'!$O$2:$Q$4,3,0)*VLOOKUP($G$1,'Lookup tables'!$K$1:$L$2,2,0)," ",A14) -> 4 Relevance | H14: =_xlfn.CONCAT(VLOOKUP(E14,'Lookup tables'!$O$2:$Q$4,3,0)*VLOOKUP($H$1,'Lookup tables'!$K$1:$L$2,2,0)," ",B14) -> 2 Fame | I14: =_xlfn.CONCAT('Lookup tables'!$L$6*VLOOKUP(E14,'Lookup tables'!$O$2:$Q$4,3,0)," ",A14) -> -2 Relevance | J14: =_xlfn.CONCAT(VLOOKUP(E14,'Lookup tables'!$O$2:$R$4,4,0)," ",A14) -> 25 Relevance | K14: The house band at the Flashlight are off this week; they’re trying out something bigger. I’ve got a few people together and I want you to front it. Do something old school so the punters think they’re safe, but be wild about it and show they’re not. | L14: Wasn’t enough to get you the regular slot at the Flashlight, but you did pretty good. Who’d have thought a punk cover of ‘I Want It That Way’ would have worked? Me neither, but it did! | M14: Ah well. No great loss. It was only a pick-up band. Could have been good, but sometimes it doesn’t work out. Still, the house band are back next week so who’ll remember?
A15: =VLOOKUP(C15,'Lookup tables'!$A$2:$B$5,2,0) -> Relevance | B15: Money | C15: Show | D15: =VLOOKUP(_xlfn.CONCAT(A15,B15),'Lookup tables'!$G$2:$H$13,2,0) -> Gig | E15: Medium | F15: =VLOOKUP(E15,'Lookup tables'!$O$2:$P$4,2,0) -> 0.6 | G15: =_xlfn.CONCAT(VLOOKUP(E15,'Lookup tables'!$O$2:$Q$4,3,0)*VLOOKUP($G$1,'Lookup tables'!$K$1:$L$2,2,0)," ",A15) -> 4 Relevance | H15: =_xlfn.CONCAT(VLOOKUP(E15,'Lookup tables'!$O$2:$Q$4,3,0)*VLOOKUP($H$1,'Lookup tables'!$K$1:$L$2,2,0)," ",B15) -> 2 Money | I15: =_xlfn.CONCAT('Lookup tables'!$L$6*VLOOKUP(E15,'Lookup tables'!$O$2:$Q$4,3,0)," ",A15) -> -2 Relevance | J15: =_xlfn.CONCAT(VLOOKUP(E15,'Lookup tables'!$O$2:$R$4,4,0)," ",A15) -> 25 Relevance | K15: There’s a slot at the Odeon that’s just opened up. I told the owners we’ll put on a show at no notice for half the price. Easy peasy! 90% of this job’s opportunism. See, people don’t like their venues empty, it costs money…. | L15: You came, you saw, you sang, you slew ‘em. If you last any length of time in this business, people are gonna talk about that gig. It came out of nowhere, you had to be there, any cliché you like, so long as it’s black… | M15: Oh dear. No, that’s not good. Can’t see you playing at the Odeon again, not unless they’re *really* hurting for bookings. We could try changing your name and sending you along in disguise, maybe…
A16: =VLOOKUP(C16,'Lookup tables'!$A$2:$B$5,2,0) -> Relevance | B16: Fun | C16: Show | D16: =VLOOKUP(_xlfn.CONCAT(A16,B16),'Lookup tables'!$G$2:$H$13,2,0) -> Festival | E16: Medium | F16: =VLOOKUP(E16,'Lookup tables'!$O$2:$P$4,2,0) -> 0.6 | G16: =_xlfn.CONCAT(VLOOKUP(E16,'Lookup tables'!$O$2:$Q$4,3,0)*VLOOKUP($G$1,'Lookup tables'!$K$1:$L$2,2,0)," ",A16) -> 4 Relevance | H16: =_xlfn.CONCAT(VLOOKUP(E16,'Lookup tables'!$O$2:$Q$4,3,0)*VLOOKUP($H$1,'Lookup tables'!$K$1:$L$2,2,0)," ",B16) -> 2 Fun | I16: =_xlfn.CONCAT('Lookup tables'!$L$6*VLOOKUP(E16,'Lookup tables'!$O$2:$Q$4,3,0)," ",A16) -> -2 Relevance | J16: =_xlfn.CONCAT(VLOOKUP(E16,'Lookup tables'!$O$2:$R$4,4,0)," ",A16) -> 25 Relevance | K16: The Offload Festival’s coming up again. Guess who’s managed to get you a one-hour slot on the Uneven Stage? Have fun, and don’t bring anything on stage with you unless you’re comfortable with the idea of it rolling gradually to the edge and falling off. | L16: Pretty good show. You did alright. The number of people singing along was greater than the number of plastic bottles of piss that were thrown, so on the whole I’d call that a win. Onto the next one! | M16: On the one hand, you bombed. No two ways about it; the crowd didn’t love ya. But on the other, this is where you develop a bit of rhino skin. Because there will be bad gigs. And everyone’s got a horror story about some festival or other. And at least it’s only Offload. They’ll take anyone so they kind of expect a minor disaster or two, just so long as people turn up.
A17: =VLOOKUP(C17,'Lookup tables'!$A$2:$B$5,2,0) -> Fame | B17: Relevance | C17: Media | D17: =VLOOKUP(_xlfn.CONCAT(A17,B17),'Lookup tables'!$G$2:$H$13,2,0) -> TV | E17: Medium | F17: =VLOOKUP(E17,'Lookup tables'!$O$2:$P$4,2,0) -> 0.6 | G17: =_xlfn.CONCAT(VLOOKUP(E17,'Lookup tables'!$O$2:$Q$4,3,0)*VLOOKUP($G$1,'Lookup tables'!$K$1:$L$2,2,0)," ",A17) -> 4 Fame | H17: =_xlfn.CONCAT(VLOOKUP(E17,'Lookup tables'!$O$2:$Q$4,3,0)*VLOOKUP($H$1,'Lookup tables'!$K$1:$L$2,2,0)," ",B17) -> 2 Relevance | I17: =_xlfn.CONCAT('Lookup tables'!$L$6*VLOOKUP(E17,'Lookup tables'!$O$2:$Q$4,3,0)," ",A17) -> -2 Fame | J17: =_xlfn.CONCAT(VLOOKUP(E17,'Lookup tables'!$O$2:$R$4,4,0)," ",A17) -> 25 Fame | K17: We’ve finally got the go-ahead to monetise MeTube content, so we’re going to record a half-hour show. Four new songs, four covers, a bit of banter in between. Make sure to rehearse a bit first! | L17: Lovely! Just look at all those thumbs! Didn’t get buried in the algorithm either. I think that’s because we linked to it from the short clips, and somehow enough of the viewers stopped doomscrolling just for long enough to click one of your links. There’s hope for humanity yet! | M17: God, that’s underwhelming. Last time I saw a number that low was on a cheque for my repeat fees for an old Doctor Who episode. Still, look on the bright side; at least some streamer didn’t upload themselves reacting to it, say nothing, and STILL pull bigger numbers – wait a minute. What? They did?!
A18: =VLOOKUP(C18,'Lookup tables'!$A$2:$B$5,2,0) -> Fame | B18: Money | C18: Media | D18: =VLOOKUP(_xlfn.CONCAT(A18,B18),'Lookup tables'!$G$2:$H$13,2,0) -> Podcast | E18: Medium | F18: =VLOOKUP(E18,'Lookup tables'!$O$2:$P$4,2,0) -> 0.6 | G18: =_xlfn.CONCAT(VLOOKUP(E18,'Lookup tables'!$O$2:$Q$4,3,0)*VLOOKUP($G$1,'Lookup tables'!$K$1:$L$2,2,0)," ",A18) -> 4 Fame | H18: =_xlfn.CONCAT(VLOOKUP(E18,'Lookup tables'!$O$2:$Q$4,3,0)*VLOOKUP($H$1,'Lookup tables'!$K$1:$L$2,2,0)," ",B18) -> 2 Money | I18: =_xlfn.CONCAT('Lookup tables'!$L$6*VLOOKUP(E18,'Lookup tables'!$O$2:$Q$4,3,0)," ",A18) -> -2 Fame | J18: =_xlfn.CONCAT(VLOOKUP(E18,'Lookup tables'!$O$2:$R$4,4,0)," ",A18) -> 25 Fame | K18: Jimmy Oxter thinks there might actually be a chance you might be funny, or at least interesting, so he’s invited you on his podcast. He might just be trying to catch you out with a prank too. | L18: Good enough, good enough. Jimmy Oxter caught you out with the whoopee cushion, you took it in your stride, proved you can take a joke as well as tell one. People like that; makes them think you’re human. | M18: What a frigging disaster! You sat on the whoopee cushion, got the fart noise, then you blew up at Jimmy Oxter? Well, I suppose we might do something with the drama later, but who’s going to ask you onto their podcast next? The problem with being a drama queen is people will think that’s all you’re good for.
A19: =VLOOKUP(C19,'Lookup tables'!$A$2:$B$5,2,0) -> Fame | B19: Fun | C19: Media | D19: =VLOOKUP(_xlfn.CONCAT(A19,B19),'Lookup tables'!$G$2:$H$13,2,0) -> Stream | E19: Medium | F19: =VLOOKUP(E19,'Lookup tables'!$O$2:$P$4,2,0) -> 0.6 | G19: =_xlfn.CONCAT(VLOOKUP(E19,'Lookup tables'!$O$2:$Q$4,3,0)*VLOOKUP($G$1,'Lookup tables'!$K$1:$L$2,2,0)," ",A19) -> 4 Fame | H19: =_xlfn.CONCAT(VLOOKUP(E19,'Lookup tables'!$O$2:$Q$4,3,0)*VLOOKUP($H$1,'Lookup tables'!$K$1:$L$2,2,0)," ",B19) -> 2 Fun | I19: =_xlfn.CONCAT('Lookup tables'!$L$6*VLOOKUP(E19,'Lookup tables'!$O$2:$Q$4,3,0)," ",A19) -> -2 Fame | J19: =_xlfn.CONCAT(VLOOKUP(E19,'Lookup tables'!$O$2:$R$4,4,0)," ",A19) -> 25 Fame | K19: You know table-top role-playing games? Brendan Brannigan thinks you might make a good bard in his fantasy game. He’ll be filming it. Write up some silly lyrics, play it mostly for laughs, but… try and play well with the others, right? Could be a regular thing if we play our cards right. | L19: The dice did not like you that day, did they? Well done on having some lyrics written for when your character screwed up. That got a few laughs, and I think some of ‘em might even have been laughing with you. | M19: The thing about role-playing games, especially the ones they record and put on streams, is they have to involve roleplay. You have to give ‘em something to work with. You just sat there like the player’s girlfriend who didn’t want to be there in the first place, and decided to act up just so nobody would invite him back either! … and who won? Not the players, not the audience, and not you.
A20: =VLOOKUP(C20,'Lookup tables'!$A$2:$B$5,2,0) -> Money | B20: Relevance | C20: Recording | D20: =VLOOKUP(_xlfn.CONCAT(A20,B20),'Lookup tables'!$G$2:$H$13,2,0) -> Collaboration | E20: Medium | F20: =VLOOKUP(E20,'Lookup tables'!$O$2:$P$4,2,0) -> 0.6 | G20: =_xlfn.CONCAT(VLOOKUP(E20,'Lookup tables'!$O$2:$Q$4,3,0)*VLOOKUP($G$1,'Lookup tables'!$K$1:$L$2,2,0)," ",A20) -> 4 Money | H20: =_xlfn.CONCAT(VLOOKUP(E20,'Lookup tables'!$O$2:$Q$4,3,0)*VLOOKUP($H$1,'Lookup tables'!$K$1:$L$2,2,0)," ",B20) -> 2 Relevance | I20: =_xlfn.CONCAT('Lookup tables'!$L$6*VLOOKUP(E20,'Lookup tables'!$O$2:$Q$4,3,0)," ",A20) -> -2 Money | J20: =_xlfn.CONCAT(VLOOKUP(E20,'Lookup tables'!$O$2:$R$4,4,0)," ",A20) -> 25 Money | K20: Barry Prunk’s recording a single (won’t be under his own name, I mean – ‘Barry’? – I ask you…) but he wants you to sing backing. He’ll sing high, you’ll sing low, or whatever they do when they want to harmonise. Just listen to this track a few times, you’ll get the idea. | L20: I think this could be the start of a beautiful friendship. Maybe Barry Prunk’ll return the favour later on! In the meantime, there’s a bit more stashed away for the album fund. Kerching, as they used to say… | M20: Never thought I’d see Barry Prunk weep. No, seriously, I think he had his tear ducts closed up during his last plastic surgery. But god, he was not in a good way after that. You didn’t have to be great, but you could at least have tried to carry a tune!
A21: =VLOOKUP(C21,'Lookup tables'!$A$2:$B$5,2,0) -> Money | B21: Fame | C21: Recording | D21: =VLOOKUP(_xlfn.CONCAT(A21,B21),'Lookup tables'!$G$2:$H$13,2,0) -> Single | E21: Medium | F21: =VLOOKUP(E21,'Lookup tables'!$O$2:$P$4,2,0) -> 0.6 | G21: =_xlfn.CONCAT(VLOOKUP(E21,'Lookup tables'!$O$2:$Q$4,3,0)*VLOOKUP($G$1,'Lookup tables'!$K$1:$L$2,2,0)," ",A21) -> 4 Money | H21: =_xlfn.CONCAT(VLOOKUP(E21,'Lookup tables'!$O$2:$Q$4,3,0)*VLOOKUP($H$1,'Lookup tables'!$K$1:$L$2,2,0)," ",B21) -> 2 Fame | I21: =_xlfn.CONCAT('Lookup tables'!$L$6*VLOOKUP(E21,'Lookup tables'!$O$2:$Q$4,3,0)," ",A21) -> -2 Money | J21: =_xlfn.CONCAT(VLOOKUP(E21,'Lookup tables'!$O$2:$R$4,4,0)," ",A21) -> 25 Money | K21: Back into the studio with you! We’ve got a song for you, and it should be a good one. It’s got most of the bits that people like. Something to sing along with, one of those vocal hooks that even howler monkeys will appreciate, and a beat anyone with a few pots and pans can copy. All we need is your voice on it. | L21: Well, it’s not top of the pops, but it charted, so somebody must have liked it. What’s ‘Top of the Pops’, you ask? Oh Christ. How old ARE you? How old am I?! | M21: Well, it flopped. That’s not a major disaster. Lots of singles flop. May take a while to recover, though; studio time costs money. We’ll try you on some other kinds of song, see if that helps.
A22: =VLOOKUP(C22,'Lookup tables'!$A$2:$B$5,2,0) -> Money | B22: Fun | C22: Recording | D22: =VLOOKUP(_xlfn.CONCAT(A22,B22),'Lookup tables'!$G$2:$H$13,2,0) -> Novelty | E22: Medium | F22: =VLOOKUP(E22,'Lookup tables'!$O$2:$P$4,2,0) -> 0.6 | G22: =_xlfn.CONCAT(VLOOKUP(E22,'Lookup tables'!$O$2:$Q$4,3,0)*VLOOKUP($G$1,'Lookup tables'!$K$1:$L$2,2,0)," ",A22) -> 4 Money | H22: =_xlfn.CONCAT(VLOOKUP(E22,'Lookup tables'!$O$2:$Q$4,3,0)*VLOOKUP($H$1,'Lookup tables'!$K$1:$L$2,2,0)," ",B22) -> 2 Fun | I22: =_xlfn.CONCAT('Lookup tables'!$L$6*VLOOKUP(E22,'Lookup tables'!$O$2:$Q$4,3,0)," ",A22) -> -2 Money | J22: =_xlfn.CONCAT(VLOOKUP(E22,'Lookup tables'!$O$2:$R$4,4,0)," ",A22) -> 25 Money | K22: You know that stupid meme that all the kids are copying that none of the grown-ups understand? We’re going to release a song about it. And when that sells, it ought to kill the meme stone dead. Everybody do the 6-7! | L22: It’s stupid, it misses the point, it sounds awful, but it’s catchy and annoying but not as annoying as the meme, and now young adults are telling kids to ‘Do the Six-Seven!’ and annoying them back. This we did for the good of humanity. | M22: Novelty singles flop all the time. Everyone’s looking for the next three-day wonder, see. Now, the worst that can happen is, years from now, when you’re a serious person, someone’s going to pull this out and play it. Best have your excuse worked out already. And develop a sense of humour, obviously!
A23: =VLOOKUP(C23,'Lookup tables'!$A$2:$B$5,2,0) -> Fun | B23: Relevance | C23: Publicity | D23: =VLOOKUP(_xlfn.CONCAT(A23,B23),'Lookup tables'!$G$2:$H$13,2,0) -> Viral | E23: Medium | F23: =VLOOKUP(E23,'Lookup tables'!$O$2:$P$4,2,0) -> 0.6 | G23: =_xlfn.CONCAT(VLOOKUP(E23,'Lookup tables'!$O$2:$Q$4,3,0)*VLOOKUP($G$1,'Lookup tables'!$K$1:$L$2,2,0)," ",A23) -> 4 Fun | H23: =_xlfn.CONCAT(VLOOKUP(E23,'Lookup tables'!$O$2:$Q$4,3,0)*VLOOKUP($H$1,'Lookup tables'!$K$1:$L$2,2,0)," ",B23) -> 2 Relevance | I23: =_xlfn.CONCAT('Lookup tables'!$L$6*VLOOKUP(E23,'Lookup tables'!$O$2:$Q$4,3,0)," ",A23) -> -2 Fun | J23: =_xlfn.CONCAT(VLOOKUP(E23,'Lookup tables'!$O$2:$R$4,4,0)," ",A23) -> 25 Fun | K23: What makes a thing go viral? I don’t know, but you’re pretty spontaneous and charismatic. Go down the club, do some stupid moves now and again. Maybe something will catch on. | L23: Okay, so now people are stopping what they’re doing and making and drinking imaginary cups of tea like they’re Marceal Marceau. But they’re doing it because you did it, and people know. | M23: Okay, you were caught being stupid, trying to force a meme that simply wouldn’t catch on. Blame it on the booze, blame it on the pills, blame it on the boogie if you have to. People are going to remember you’re ‘cringe’, like the youngsters say. But you know what? Here’s a secret for you: EVERYONE IS CRINGE. And sooner or later they’ll all be cringe too. And then you’ll be even.
A24: =VLOOKUP(C24,'Lookup tables'!$A$2:$B$5,2,0) -> Fun | B24: Fame | C24: Publicity | D24: =VLOOKUP(_xlfn.CONCAT(A24,B24),'Lookup tables'!$G$2:$H$13,2,0) -> Prank | E24: Medium | F24: =VLOOKUP(E24,'Lookup tables'!$O$2:$P$4,2,0) -> 0.6 | G24: =_xlfn.CONCAT(VLOOKUP(E24,'Lookup tables'!$O$2:$Q$4,3,0)*VLOOKUP($G$1,'Lookup tables'!$K$1:$L$2,2,0)," ",A24) -> 4 Fun | H24: =_xlfn.CONCAT(VLOOKUP(E24,'Lookup tables'!$O$2:$Q$4,3,0)*VLOOKUP($H$1,'Lookup tables'!$K$1:$L$2,2,0)," ",B24) -> 2 Fame | I24: =_xlfn.CONCAT('Lookup tables'!$L$6*VLOOKUP(E24,'Lookup tables'!$O$2:$Q$4,3,0)," ",A24) -> -2 Fun | J24: =_xlfn.CONCAT(VLOOKUP(E24,'Lookup tables'!$O$2:$R$4,4,0)," ",A24) -> 25 Fun | K24: You know that little runt Jimmy Flaherty? Did all those ‘prank’ videos? He’s started going to Flashbangs, and I know the guy who owns that club. We’re going to get the bouncers to give him the runaround, make him look like Billy No Mates, then you’re gonna come out and spring it on him. Do you remember Jeremy Beadle? … no? Christ, how old ARE you? … how old am I?! | L24: Noticed that genuine adulation and cheering? That might not be for your singing, but for doing something they never got the chance to do, or never had the guts to do. And you know what? that might just be better! | M24: Oh, now this is just embarrassing. That backfired. That backfired and he harrassed you all night, ruining your day – probably your week too. Still, chin up! It could be a lot worse. You could have made him look like the victim. God help us if Jimmy Flaherty’s in the right, eh?
A25: =VLOOKUP(C25,'Lookup tables'!$A$2:$B$5,2,0) -> Fun | B25: Money | C25: Publicity | D25: Influencer | E25: Medium | F25: =VLOOKUP(E25,'Lookup tables'!$O$2:$P$4,2,0) -> 0.6 | G25: =_xlfn.CONCAT(VLOOKUP(E25,'Lookup tables'!$O$2:$Q$4,3,0)*VLOOKUP($G$1,'Lookup tables'!$K$1:$L$2,2,0)," ",A25) -> 4 Fun | H25: =_xlfn.CONCAT(VLOOKUP(E25,'Lookup tables'!$O$2:$Q$4,3,0)*VLOOKUP($H$1,'Lookup tables'!$K$1:$L$2,2,0)," ",B25) -> 2 Money | I25: =_xlfn.CONCAT('Lookup tables'!$L$6*VLOOKUP(E25,'Lookup tables'!$O$2:$Q$4,3,0)," ",A25) -> -2 Fun | J25: =_xlfn.CONCAT(VLOOKUP(E25,'Lookup tables'!$O$2:$R$4,4,0)," ",A25) -> 25 Fun | K25: Welcome to the world of make-up influencing. Splotti (Apparently that’s her legal name now) is trying to push her ‘Pop Star’ range, and guess whose face gets to be her canvas? | L25: I don’t know what I expected. But somehow you managed to make something of it. Even got her to come up with some kind of look you can try on stage. Let’s just hope she doesn’t want to go into singing. What can I do with a girl named ‘Splotti’? | M25: Who’d have thought make-up influencers would be such drama queens? Anyone who’s met one, that’s who! Somehow they’ve spun the whole sorry affair into you victimising them and now everyone’s saying you’re ‘cancelled.’ Nothing for it now but to make a crappy apology video, with you singing a song about drama while playing a ukulele. No, wait a minute, what am I thinking? That’s an awful idea.
A26: =VLOOKUP(C26,'Lookup tables'!$A$2:$B$5,2,0) -> Relevance | B26: Fame | C26: Show | D26: Club | E26: Hard | F26: =VLOOKUP(E26,'Lookup tables'!$O$2:$P$4,2,0) -> 0.45 | G26: =_xlfn.CONCAT(VLOOKUP(E26,'Lookup tables'!$O$2:$Q$4,3,0)*VLOOKUP($G$1,'Lookup tables'!$K$1:$L$2,2,0)," ",A26) -> 6 Relevance | H26: =_xlfn.CONCAT(VLOOKUP(E26,'Lookup tables'!$O$2:$Q$4,3,0)*VLOOKUP($H$1,'Lookup tables'!$K$1:$L$2,2,0)," ",B26) -> 3 Fame | I26: =_xlfn.CONCAT('Lookup tables'!$L$6*VLOOKUP(E26,'Lookup tables'!$O$2:$Q$4,3,0)," ",A26) -> -3 Relevance | J26: =_xlfn.CONCAT(VLOOKUP(E26,'Lookup tables'!$O$2:$R$4,4,0)," ",A26) -> 40 Relevance | K26: The Flashlight is under new management, so it’s all change. They’ve got this idea of ‘residencies’ now: the house band changes every month. Four gigs, then off to something else. I’m not saying the job’s yours, but it could be, if you impress the new bigwigs. Get in there and knock ‘em dead and that’s at least twelve shows at a club that is still inexplicably pretty hot. | L26: Well, you tried… and you got it! Four weeks at the Flashlight, a show every Friday, Saturday, and Sunday. Plus of course rehearsals and such. You’re practically gonna be living there. Don’t let ‘em charge you rent, though. Even if you set up a campbed and a space heater. | M26: The audition didn’t go so well. In fact it was terrible. You’re one of dozens of also-rans. I heard a few discouraging voices, but… the hell with ‘em. There’s always gonna be people telling you you’ve lost it, or you never hard it. Just have to put up with it and carry on regardless. That’s showbiz!
A27: =VLOOKUP(C27,'Lookup tables'!$A$2:$B$5,2,0) -> Relevance | B27: Money | C27: Show | D27: =VLOOKUP(_xlfn.CONCAT(A27,B27),'Lookup tables'!$G$2:$H$13,2,0) -> Gig | E27: Hard | F27: =VLOOKUP(E27,'Lookup tables'!$O$2:$P$4,2,0) -> 0.45 | G27: =_xlfn.CONCAT(VLOOKUP(E27,'Lookup tables'!$O$2:$Q$4,3,0)*VLOOKUP($G$1,'Lookup tables'!$K$1:$L$2,2,0)," ",A27) -> 6 Relevance | H27: =_xlfn.CONCAT(VLOOKUP(E27,'Lookup tables'!$O$2:$Q$4,3,0)*VLOOKUP($H$1,'Lookup tables'!$K$1:$L$2,2,0)," ",B27) -> 3 Money | I27: =_xlfn.CONCAT('Lookup tables'!$L$6*VLOOKUP(E27,'Lookup tables'!$O$2:$Q$4,3,0)," ",A27) -> -3 Relevance | J27: =_xlfn.CONCAT(VLOOKUP(E27,'Lookup tables'!$O$2:$R$4,4,0)," ",A27) -> 40 Relevance | K27: HeeBGB’s decided to take a chance on you, seeing as how you’re one of the up-and-coming acts. ‘Someone to watch’, I heard the manager say. He MIGHT have said ‘preferably through the viewfinder of a telescopic sight attached to a high-powered rifle’ but I’m pretty sure he was joking when he said that. Still, you’ve got a couple of hours to show them you’re worth a couple of hours, so get warmed up and ready to go. This could be big! | L27: HeeBGB used to be a great club, back in the day. And now you’re playing there. I don’t know how those two statements relate to each other yet. You work it out! | M27: Christ, I’ve never seen a place so empty! And off the back of that another couple of gigs have cancelled. Not saying your career’s over, but let’s not sugar-coat this; it’s a setback. Maybe we were a bit premature trying to play at HeeBGB’s; somewhere a bit lower key might work better. Earn your dues a bit.
A28: =VLOOKUP(C28,'Lookup tables'!$A$2:$B$5,2,0) -> Relevance | B28: Fun | C28: Show | D28: =VLOOKUP(_xlfn.CONCAT(A28,B28),'Lookup tables'!$G$2:$H$13,2,0) -> Festival | E28: Hard | F28: =VLOOKUP(E28,'Lookup tables'!$O$2:$P$4,2,0) -> 0.45 | G28: =_xlfn.CONCAT(VLOOKUP(E28,'Lookup tables'!$O$2:$Q$4,3,0)*VLOOKUP($G$1,'Lookup tables'!$K$1:$L$2,2,0)," ",A28) -> 6 Relevance | H28: =_xlfn.CONCAT(VLOOKUP(E28,'Lookup tables'!$O$2:$Q$4,3,0)*VLOOKUP($H$1,'Lookup tables'!$K$1:$L$2,2,0)," ",B28) -> 3 Fun | I28: =_xlfn.CONCAT('Lookup tables'!$L$6*VLOOKUP(E28,'Lookup tables'!$O$2:$Q$4,3,0)," ",A28) -> -3 Relevance | J28: =_xlfn.CONCAT(VLOOKUP(E28,'Lookup tables'!$O$2:$R$4,4,0)," ",A28) -> 40 Relevance | K28: I don’t know if it’s mass hysteria or just an outbreak of botulism that hospitalised everyone responsible for booking the acts, but you’re on to headline on the Wobbly Stage at the Offload Festival. Headline act of the year! Or of the next couple of months. Never can tell when the next Offload’s gonna be, see. Legend has it they’re still trying to make their money back for the first one. Still, even if they added you just for a joke, turn up and prove ‘em wrong. Or right. Just don’t be boring, that’s the main thing. | L28: How many dozens of people headlined at the Offload Festival over the years? Loads. I couldn’t be arsed to count. But you have now. And you’re on the list. That could be on a pub quiz machine later. Fancy that! You could be going for a drink, spend a couple of quid on the quizzy, and a question could come up with you on it! Who says this industry doesn’t pay? | M28: What an absolute shower! Don’t think I’ve seen so many bottles of pee airborne at one time before. Let’s face it, they didn’t like you. The worst bit of it is we’re gonna have to watch the show again, and work out why. Was it the songs? Was it the way you sang? Was it the time you told them you were the Son of God and they should worship you? Who can tell?
A29: =VLOOKUP(C29,'Lookup tables'!$A$2:$B$5,2,0) -> Fame | B29: Relevance | C29: Media | D29: =VLOOKUP(_xlfn.CONCAT(A29,B29),'Lookup tables'!$G$2:$H$13,2,0) -> TV | E29: Hard | F29: =VLOOKUP(E29,'Lookup tables'!$O$2:$P$4,2,0) -> 0.45 | G29: =_xlfn.CONCAT(VLOOKUP(E29,'Lookup tables'!$O$2:$Q$4,3,0)*VLOOKUP($G$1,'Lookup tables'!$K$1:$L$2,2,0)," ",A29) -> 6 Fame | H29: =_xlfn.CONCAT(VLOOKUP(E29,'Lookup tables'!$O$2:$Q$4,3,0)*VLOOKUP($H$1,'Lookup tables'!$K$1:$L$2,2,0)," ",B29) -> 3 Relevance | I29: =_xlfn.CONCAT('Lookup tables'!$L$6*VLOOKUP(E29,'Lookup tables'!$O$2:$Q$4,3,0)," ",A29) -> -3 Fame | J29: =_xlfn.CONCAT(VLOOKUP(E29,'Lookup tables'!$O$2:$R$4,4,0)," ",A29) -> 40 Fame | K29: Remember TV? That box old people keep in their lounges, sometimes shows music? Well, The Half Show want you to appear. Chat a bit, sing a bit, pop stars used to do that all the time before everything went online. Used to have whole channels devoted to it for a while. Weird. | L29: Grown-up people know about you now. Just think! Kids and adults alike know about you and your music. And now that’s happened, they can all come together and-- what am I talking about? That almost never happens. | M29: Yes, I know the audience applauded. They were very polite, very perfunctory. But when the host smiled and praised you that smile was nowhere near her eyes. It’s one of those shows where they just describe what you did by saying your name and that you sang a song. Gotta liven that up a bit. The worst thing about it, the unforgiveable thing, was it was BORING. Boring, boring, boring…
A30: =VLOOKUP(C30,'Lookup tables'!$A$2:$B$5,2,0) -> Fame | B30: Money | C30: Media | D30: =VLOOKUP(_xlfn.CONCAT(A30,B30),'Lookup tables'!$G$2:$H$13,2,0) -> Podcast | E30: Hard | F30: =VLOOKUP(E30,'Lookup tables'!$O$2:$P$4,2,0) -> 0.45 | G30: =_xlfn.CONCAT(VLOOKUP(E30,'Lookup tables'!$O$2:$Q$4,3,0)*VLOOKUP($G$1,'Lookup tables'!$K$1:$L$2,2,0)," ",A30) -> 6 Fame | H30: =_xlfn.CONCAT(VLOOKUP(E30,'Lookup tables'!$O$2:$Q$4,3,0)*VLOOKUP($H$1,'Lookup tables'!$K$1:$L$2,2,0)," ",B30) -> 3 Money | I30: =_xlfn.CONCAT('Lookup tables'!$L$6*VLOOKUP(E30,'Lookup tables'!$O$2:$Q$4,3,0)," ",A30) -> -3 Fame | J30: =_xlfn.CONCAT(VLOOKUP(E30,'Lookup tables'!$O$2:$R$4,4,0)," ",A30) -> 40 Fame | K30: Seems people are still reading books, if you can believe that. Almost makes you feel hope for humanity, doesn’t it? Still, Caitlin Sandford’s got this literary podcast. Her, pal, and a couple of guests read a book and talk everyone’s ears off for an hour. The first half hour’s usually rubbish because everyone’s still sober and a bit nervous, but the last half hour’s usually a riot. So, take this book, read it, pick some bits you like, neck some prosecco and hold forth! | L30: It’s always nice to be able to add stuff to your CV. “I recorded a song and it charted.” “I played at the Flashlight.” And now, best of all, “I’ve read a book.” If ever you get into a pissing contest with someone, save that for last. Wins every time. | M30: Got stuck into the Prosecco a bit early, didn’t you? I’m afraid that was a bit of a shambles. That bit where you said you fell asleep at the contents page and didn’t read any further didn’t go down as well as you might have liked. And all the Harry Potter and Frodo Baggins jokes went over like the proverbial lead balloon.
A31: =VLOOKUP(C31,'Lookup tables'!$A$2:$B$5,2,0) -> Fame | B31: Fun | C31: Media | D31: =VLOOKUP(_xlfn.CONCAT(A31,B31),'Lookup tables'!$G$2:$H$13,2,0) -> Stream | E31: Hard | F31: =VLOOKUP(E31,'Lookup tables'!$O$2:$P$4,2,0) -> 0.45 | G31: =_xlfn.CONCAT(VLOOKUP(E31,'Lookup tables'!$O$2:$Q$4,3,0)*VLOOKUP($G$1,'Lookup tables'!$K$1:$L$2,2,0)," ",A31) -> 6 Fame | H31: =_xlfn.CONCAT(VLOOKUP(E31,'Lookup tables'!$O$2:$Q$4,3,0)*VLOOKUP($H$1,'Lookup tables'!$K$1:$L$2,2,0)," ",B31) -> 3 Fun | I31: =_xlfn.CONCAT('Lookup tables'!$L$6*VLOOKUP(E31,'Lookup tables'!$O$2:$Q$4,3,0)," ",A31) -> -3 Fame | J31: =_xlfn.CONCAT(VLOOKUP(E31,'Lookup tables'!$O$2:$R$4,4,0)," ",A31) -> 40 Fame | K31: You know what’s really stupid? Reaction streaming. Watch some videos, react to what you see, and people watch you watching that. It’s like that Gigglebox programme, I think. Still, we’re gonna give it a try, might catch on. Just have some catchphrases, take the piss, be funny, be obnoxious, be drunk, just don’t be boring. There are only a few people who can sit, watch, and not react to something and make money from it, and as much as I love money, I’d hate for it to be you. | L31: Well now! Weren’t you just a little riff machine! Thirty short videos, and you had something to say about all of them that wasn’t just ‘wow…’ or ‘oh my god…’ Some of the jokes even made ME chuckle. | M31: The key to reaction videos, the important thing about them, the OPERATIVE WORD, you might say, is ‘reaction’. I don’t know what you were doing, but it wasn’t reacting. You got some views, and some people found out about them and got you some more views, but this little bearded bloke with tattoos and long hair went and did the most savage frigging commentary I’ve heard, with a vocabulary almost as big as mine! This obviously wasn’t the medium for you. We’ll try you on something else, I think; maybe leave the commentary to the people who’re good at commenting.
A32: =VLOOKUP(C32,'Lookup tables'!$A$2:$B$5,2,0) -> Money | B32: Relevance | C32: Recording | D32: =VLOOKUP(_xlfn.CONCAT(A32,B32),'Lookup tables'!$G$2:$H$13,2,0) -> Collaboration | E32: Hard | F32: =VLOOKUP(E32,'Lookup tables'!$O$2:$P$4,2,0) -> 0.45 | G32: =_xlfn.CONCAT(VLOOKUP(E32,'Lookup tables'!$O$2:$Q$4,3,0)*VLOOKUP($G$1,'Lookup tables'!$K$1:$L$2,2,0)," ",A32) -> 6 Money | H32: =_xlfn.CONCAT(VLOOKUP(E32,'Lookup tables'!$O$2:$Q$4,3,0)*VLOOKUP($H$1,'Lookup tables'!$K$1:$L$2,2,0)," ",B32) -> 3 Relevance | I32: =_xlfn.CONCAT('Lookup tables'!$L$6*VLOOKUP(E32,'Lookup tables'!$O$2:$Q$4,3,0)," ",A32) -> -3 Money | J32: =_xlfn.CONCAT(VLOOKUP(E32,'Lookup tables'!$O$2:$R$4,4,0)," ",A32) -> 40 Money | K32: Do you remember supergroups at all? Members of famous groups would join up with members of other famous groups to make even bigger groups. Well, you’ve got a slot in one of those. Not that you’re famous, well, not FAMOUS famous, but you’re on your way. We’re gonna call you the Select. Oh no, wait, that sounds too much like the Selecter. The Selection? Nah, that’s been done too, innit. Well, whatever we call you, we’ve got you some studio time. So get in there and make some noise! | L32: What a nightmare! So many egos in one room! And that’s before everyone else turned up! Still, something seemed to happen, we’ve got an hour’s worth of sound that’s actually usable, and you never know, if we get a good engineer to fiddle with it, it might even be good. Well done for keeping your marbles. Or most of ‘em. | M32: All egos were firmly checked at the door, as was all willingness to do anything. I’m not saying you were solely to blame, but… you weren’t much help, were you? I think we’ll be lucky to scrape together five minutes of all of that. Best let everyone get back to their own knitting, because putting you all together was a recipe for disaster. What? Mix metaphors? Me? And where was this shining wit back in the studio when we needed it, eh?
A33: =VLOOKUP(C33,'Lookup tables'!$A$2:$B$5,2,0) -> Money | B33: Fame | C33: Recording | D33: =VLOOKUP(_xlfn.CONCAT(A33,B33),'Lookup tables'!$G$2:$H$13,2,0) -> Single | E33: Hard | F33: =VLOOKUP(E33,'Lookup tables'!$O$2:$P$4,2,0) -> 0.45 | G33: =_xlfn.CONCAT(VLOOKUP(E33,'Lookup tables'!$O$2:$Q$4,3,0)*VLOOKUP($G$1,'Lookup tables'!$K$1:$L$2,2,0)," ",A33) -> 6 Money | H33: =_xlfn.CONCAT(VLOOKUP(E33,'Lookup tables'!$O$2:$Q$4,3,0)*VLOOKUP($H$1,'Lookup tables'!$K$1:$L$2,2,0)," ",B33) -> 3 Fame | I33: =_xlfn.CONCAT('Lookup tables'!$L$6*VLOOKUP(E33,'Lookup tables'!$O$2:$Q$4,3,0)," ",A33) -> -3 Money | J33: =_xlfn.CONCAT(VLOOKUP(E33,'Lookup tables'!$O$2:$R$4,4,0)," ",A33) -> 40 Money | K33: Back in the studio. We’ve got you some time with Brian Ono. No relation. But he knows his way around a mixing desk and he reckons he could make you sound good. Try not to pay too much attention when he does stuff with his tarot cards, just smile, nod, and do whatever he says if it makes sense. All genius engineers are weirdoes. And just maybe this weirdo engineer is a genius. Stranger things have happened! | L33: Looks like you’ve got a bit of a hit on your hands here. If only there was some sort of program, on TV perhaps, that helped us keep track of that. They could get singers and bands on, maybe get different DJs to host it each week and engage in light-hearted banter… until the next Operation Yewtree, anyway… | M33: I don’t know what went wrong! We had the right voice, the right song, the right tune… well, I’m gonna give you a life lesson here, rather than my usual bollocks. Sometimes it is possible to do everything right, and get nowhere. That’s just how it is. Especially in an industry as insane as this one. Maybe the time for this single hasn’t come yet. Maybe we can release it again later.
A34: =VLOOKUP(C34,'Lookup tables'!$A$2:$B$5,2,0) -> Money | B34: Fun | C34: Recording | D34: =VLOOKUP(_xlfn.CONCAT(A34,B34),'Lookup tables'!$G$2:$H$13,2,0) -> Novelty | E34: Hard | F34: =VLOOKUP(E34,'Lookup tables'!$O$2:$P$4,2,0) -> 0.45 | G34: =_xlfn.CONCAT(VLOOKUP(E34,'Lookup tables'!$O$2:$Q$4,3,0)*VLOOKUP($G$1,'Lookup tables'!$K$1:$L$2,2,0)," ",A34) -> 6 Money | H34: =_xlfn.CONCAT(VLOOKUP(E34,'Lookup tables'!$O$2:$Q$4,3,0)*VLOOKUP($H$1,'Lookup tables'!$K$1:$L$2,2,0)," ",B34) -> 3 Fun | I34: =_xlfn.CONCAT('Lookup tables'!$L$6*VLOOKUP(E34,'Lookup tables'!$O$2:$Q$4,3,0)," ",A34) -> -3 Money | J34: =_xlfn.CONCAT(VLOOKUP(E34,'Lookup tables'!$O$2:$R$4,4,0)," ",A34) -> 40 Money | K34: Fancy a bit of a laugh? ‘course you do. Some group on one of those social networks has a sort of in-joke, and they’ve made it into a song, and after a few bright sparks did some different versions of it, they decided to crowdfund a proper recording of it. Somehow, don’t ask me how, I think I’ve persuaded them to ask you to sing on it. Even if they’ve not come round yet, I reckon if you turn up anyway they’ll take it as a sign and let you on anyway. So, download these mp3s to your phone, have a listen, and we’ll get you there to record when it’s time. | L34: How do we measure the success of this? I’m not sure. I mean, they saved up the money to pay you, and ordered a few thousand physical copies pressed, they’ve all been distributed. But it’s not really OUT THERE in the wild, is it? We just found a group and gave ‘em what they wanted, and… you know, this’d bug me if I wasn’t feeling so bloody content with the job we did! | M34: I think I might have mentioned before; for every novelty single that hits, there are plenty that don’t. It’s just a matter of opportunism, and leaping onto an idea that might or might not be successful. Problem is, there’s a bit of a black art to it. And what we’ve all done this time is leapt at it in a kind of rugby tackle, only to end up in a tangle of limbs and bruised egos. Speaking of which, my back’s playing up. I think I need a lie-down. I’ll call you tomorrow.
A35: =VLOOKUP(C35,'Lookup tables'!$A$2:$B$5,2,0) -> Fun | B35: Relevance | C35: Publicity | D35: =VLOOKUP(_xlfn.CONCAT(A35,B35),'Lookup tables'!$G$2:$H$13,2,0) -> Viral | E35: Hard | F35: =VLOOKUP(E35,'Lookup tables'!$O$2:$P$4,2,0) -> 0.45 | G35: =_xlfn.CONCAT(VLOOKUP(E35,'Lookup tables'!$O$2:$Q$4,3,0)*VLOOKUP($G$1,'Lookup tables'!$K$1:$L$2,2,0)," ",A35) -> 6 Fun | H35: =_xlfn.CONCAT(VLOOKUP(E35,'Lookup tables'!$O$2:$Q$4,3,0)*VLOOKUP($H$1,'Lookup tables'!$K$1:$L$2,2,0)," ",B35) -> 3 Relevance | I35: =_xlfn.CONCAT('Lookup tables'!$L$6*VLOOKUP(E35,'Lookup tables'!$O$2:$Q$4,3,0)," ",A35) -> -3 Fun | J35: =_xlfn.CONCAT(VLOOKUP(E35,'Lookup tables'!$O$2:$R$4,4,0)," ",A35) -> 40 Fun | K35: Okay, pay attention, ‘cause this could be big. Joey Itch, who’s been animating stuff on the internet for years and years, liked one of your songs. No, not that one. The one nobody can make out the lyrics for, that one. So he wants to do a misheard lyrics video, but he reckons he can afford you for a day; just go along, sing the song – normal version, and with his lyrics – and let him take some photos of you in stage dress. He’ll animate it up, and it’ll catch on – ‘cause it sort of has already. Ready to be in a cartoon? | L35: Mission accomplished! I’ve watched it ten times, I’m bloody annoyed with it now. It’s all the dance moves he got your cartoon self to do, I’m not sure they’re physically possible. Unless you can do a splits and make your knees bend backwards, then get up and do it again. Actually, is there some way you can do that on the stage? | M35: Huh. That one didn’t work out. Sometimes the joke doesn’t land, the tune doesn’t catch, and the animation wrings no smiles from the bovine audience. Maybe it’s a slow burner. Maybe it’s just something we can say is part of a larger body of work. But whatever it is, it’s not a hit. Onto the next stunt!
A36: =VLOOKUP(C36,'Lookup tables'!$A$2:$B$5,2,0) -> Fun | B36: Fame | C36: Publicity | D36: =VLOOKUP(_xlfn.CONCAT(A36,B36),'Lookup tables'!$G$2:$H$13,2,0) -> Prank | E36: Hard | F36: =VLOOKUP(E36,'Lookup tables'!$O$2:$P$4,2,0) -> 0.45 | G36: =_xlfn.CONCAT(VLOOKUP(E36,'Lookup tables'!$O$2:$Q$4,3,0)*VLOOKUP($G$1,'Lookup tables'!$K$1:$L$2,2,0)," ",A36) -> 6 Fun | H36: =_xlfn.CONCAT(VLOOKUP(E36,'Lookup tables'!$O$2:$Q$4,3,0)*VLOOKUP($H$1,'Lookup tables'!$K$1:$L$2,2,0)," ",B36) -> 3 Fame | I36: =_xlfn.CONCAT('Lookup tables'!$L$6*VLOOKUP(E36,'Lookup tables'!$O$2:$Q$4,3,0)," ",A36) -> -3 Fun | J36: =_xlfn.CONCAT(VLOOKUP(E36,'Lookup tables'!$O$2:$R$4,4,0)," ",A36) -> 40 Fun | K36: Now you’re getting big, if you’re going to pull pranks you’ve got to think big. Nothing mean-spirited, though. What I’m thinking is we do a small show, a few hundred seats; we get in touch with the club owner in advance, and we trap all the chairs with whoopee cushions. Well, yes, I DO keep doing the whoopee cushion gag. Fart jokes are always funny. And I used to own a joke shop and I was never able to shift all the stock, so I’ve got a few thousand of these buggers to use in one stunt or another. Don’t knock it, the Lord’s provided and we’ve got the chance to do something funny on the cheap. We’ll record the show, put it on YouTube, farts and all. Maybe put one on your stool as well, just to show you’re not above it all. Make sure you’ve got a line to say when you sit on it, eh? | L36: Okay, playing all those sentimental songs, a few quiet numbers, was a stroke of GENIUS. The quieter the song, the louder the fart. And the poetry reading, well, I don’t think anyone knew where to look from that, and I’m sure Dylan Thomas is turning in his grave, but it doesn’t matter. Fart jokes are funny, especially when you try to make everything else extra solemn. Job well done! | M36: Apparently these days fart jokes aren’t funny at all. How was I to know that in the light of his death from chronic flatulence and diarrhoea, people have decided to like a certain late world leader after all? But no, he’s gone, never mind what he did, fart jokes are all in appalling taste even if they’ve got nothing to do with President Shart. Some people ain’t got no sense of humour!
A37: =VLOOKUP(C37,'Lookup tables'!$A$2:$B$5,2,0) -> Fun | B37: Money | C37: Publicity | D37: Influencer | E37: Hard | F37: =VLOOKUP(E37,'Lookup tables'!$O$2:$P$4,2,0) -> 0.45 | G37: =_xlfn.CONCAT(VLOOKUP(E37,'Lookup tables'!$O$2:$Q$4,3,0)*VLOOKUP($G$1,'Lookup tables'!$K$1:$L$2,2,0)," ",A37) -> 6 Fun | H37: =_xlfn.CONCAT(VLOOKUP(E37,'Lookup tables'!$O$2:$Q$4,3,0)*VLOOKUP($H$1,'Lookup tables'!$K$1:$L$2,2,0)," ",B37) -> 3 Money | I37: =_xlfn.CONCAT('Lookup tables'!$L$6*VLOOKUP(E37,'Lookup tables'!$O$2:$Q$4,3,0)," ",A37) -> -3 Fun | J37: =_xlfn.CONCAT(VLOOKUP(E37,'Lookup tables'!$O$2:$R$4,4,0)," ",A37) -> 40 Fun | K37: Have you heard of MrBees? Of course you have. Apparently he’s the most famous person in the world now, for doing whatever the Hell it is he does. Well, he’s in the country for the next few months, and he wants to do a local version of one of this challenges. He says there’s a 20 grand prize for who can withstand his electric fence, it all smells like a bit of a scam to me; but everyone else’ll be there so you may be as well. If it all goes pear-shaped you can at least get some camera time out of it and we can trade off the drama later. Unless there’s a non-disclosure agreement or something. We’ll look at the contract later, and if it stinks we’ll kick a stink up about that instead. | L37: Well, we got the money. And we had some fun. Mainly because I got everyone together in advance to work out what MrBees was up to, and get you all prepared. He didn’t see that coming, did he? Especially when you formed that human chain and zapped him! Still, he paid up, and even if twenty grand between twenty people (minus my cut, of course) isn’t much, it still means the joke’s on him. | M37: *Tch*. Nobody came out of that looking good, did they? The only real upside to that is Mr Bees looked like a bit of an arse as well. Which is only fair, because frankly he is. He looked like a manipulative, fame-hungry sadist, with a load of manipulative, fame-hungry little masochists prepared to perform for the crumbs that fell from his plate, and I’m sorry to say you did too. But at least everyone else did as well. That’s some consolation. Not much, but it is something.

Sheet Lookup tables
A1: Category | B1: Primary Stat | E1: Major Stat | F1: Minor Stat | G1: Key | H1: Description | K1: Minor Reward | L1: 1 | O1: Description | P1: Base Chance | Q1: Difficulty | R1: Prerequisite
A2: Publicity | B2: Fun | D2: Show | E2: Relevance | F2: Fame | G2: =_xlfn.CONCAT(E2,F2) -> RelevanceFame | H2: Headline | K2: Major Reward | L2: 2 | O2: Easy | P2: 0.75 | Q2: 1 | R2: 10
A3: Media | B3: Fame | D3: Show | E3: Relevance | F3: Money | G3: =_xlfn.CONCAT(E3,F3) -> RelevanceMoney | H3: Gig | O3: Medium | P3: 0.6 | Q3: 2 | R3: 25
A4: Recording | B4: Money | D4: Show | E4: Relevance | F4: Fun | G4: =_xlfn.CONCAT(E4,F4) -> RelevanceFun | H4: Festival | O4: Hard | P4: 0.45 | Q4: 3 | R4: 40
A5: Show | B5: Relevance | D5: Media | E5: Fame | F5: Relevance | G5: =_xlfn.CONCAT(E5,F5) -> FameRelevance | H5: TV
D6: Media | E6: Fame | F6: Money | G6: =_xlfn.CONCAT(E6,F6) -> FameMoney | H6: Podcast | K6: Failure Penalty | L6: -1
D7: Media | E7: Fame | F7: Fun | G7: =_xlfn.CONCAT(E7,F7) -> FameFun | H7: Stream
D8: Recording | E8: Money | F8: Relevance | G8: =_xlfn.CONCAT(E8,F8) -> MoneyRelevance | H8: Collaboration
D9: Recording | E9: Money | F9: Fame | G9: =_xlfn.CONCAT(E9,F9) -> MoneyFame | H9: Single
D10: Recording | E10: Money | F10: Fun | G10: =_xlfn.CONCAT(E10,F10) -> MoneyFun | H10: Novelty
D11: Publicity | E11: Fun | F11: Relevance | G11: =_xlfn.CONCAT(E11,F11) -> FunRelevance | H11: Viral
D12: Publicity | E12: Fun | F12: Fame | G12: =_xlfn.CONCAT(E12,F12) -> FunFame | H12: Prank
D13: Publicity | E13: Fun | F13: Money | G13: =_xlfn.CONCAT(E13,F13) -> FunMoney | H13: Influencer
